ddlpy2/__init__.py
ddlpy2/cli.py
ddlpy2/ddlpy2.py
ddlpy2/endpoints.json
ddlpy2/utils.py
ddlpy2/waterinfo.py
waterinfo_ddlpy-0.2.2.dist-info/LICENSE
waterinfo_ddlpy-0.2.2.dist-info/METADATA
waterinfo_ddlpy-0.2.2.dist-info/WHEEL
waterinfo_ddlpy-0.2.2.dist-info/top_level.txt
waterinfo_ddlpy-0.2.2.dist-info/RECORD
