Metadata-Version: 2.1
Name: waterinfo-ddlpy
Version: 0.2.2
Summary: An extended version of rws-ddlpy for using the API to collect water data observations from Dutch Rijkswaterstaat (DDL, waterinfo.rws.nl)
Author-email: Matthijs Draijer <git@draijer.org>
Project-URL: Homepage, https://github.com/physje/ddlpy/
Keywords: rws, waterinfo, ddlpy, rijkswaterstaat
Classifier: Development Status :: 3 - Alpha
Classifier: Programming Language :: Python :: 3
Classifier: License :: OSI Approved :: MIT License
Classifier: Operating System :: OS Independent
Requires-Python: >=3.8
License-File: LICENSE
Requires-Dist: pandas
Requires-Dist: numpy
Requires-Dist: click
Requires-Dist: datetime
Requires-Dist: python-dateutil >=2.8
